tirith/__init__.py
tirith/client.py
tirith/monitor.py
tirith/components/__init__.py
tirith/components/monitor.py
tirith/components/sensor.py
tirith-0.2.2.dist-info/DESCRIPTION.rst
tirith-0.2.2.dist-info/METADATA
tirith-0.2.2.dist-info/RECORD
tirith-0.2.2.dist-info/WHEEL
tirith-0.2.2.dist-info/entry_points.txt
tirith-0.2.2.dist-info/metadata.json
tirith-0.2.2.dist-info/top_level.txt
