Metadata-Version: 2.0
Name: tirith
Version: 0.2.2
Summary: Monitoring software
Home-page: https://github.com/utfsmlabs/tirith
Author: René Mujica Moreau
Author-email: rene.mujica.m@gmail.com
License: MIT
Keywords: monitoring
Platform: UNKNOWN
Classifier: Development Status :: 1 - Planning
Classifier: Intended Audience :: System Administrators
Classifier: Topic :: System :: Monitoring
Classifier: License :: OSI Approved :: MIT License
Classifier: Programming Language :: Python :: 3.5
Requires-Dist: autobahn
